{
    "query": "show execution of this subtask",
    "programs":
    [
        "FilterType tasks root",
        "FilterAttr task_id current_task_id prev",
        "FilterType subtasks prev",
        "FilterAttr subtask_id current_subtask_id prev",
        "FilterType instructions prev",
        "FilterType actions prev"
    ],
    "context":
    {
        "current_task_id": "32-11-61-000-802",
        "current_subtask_id": "32-11-61-020-008",
        "current_instruction_order": "1"
    },
    "reply":
    [
        {
            "detach":
            [
                "49",
                "47"
            ]
        },
        {
            "detach":
            [
                "50",
                "47"
            ]
        },
        {
            "detach":
            [
                "48",
                "47"
            ]
        },
        {
            "detach":
            [
                "47",
                "52"
            ]
        },
        {
            "detach":
            [
                "54",
                "52"
            ]
        },
        {
            "detach":
            [
                "53",
                "52"
            ]
        },
        {
            "detach":
            [
                "52",
                "51"
            ]
        }
    ]
}